libreforms_fastapi/__init__.py
libreforms_fastapi/__metadata__.py
libreforms_fastapi/app/__init__.py
libreforms_fastapi/app/static/favicon.ico
libreforms_fastapi/app/static/css/bootstrap-darkly-5.3.1.css
libreforms_fastapi/app/static/css/bootstrap-flatly-5.3.1.css
libreforms_fastapi/app/static/css/datatables.css
libreforms_fastapi/app/static/css/style.css
libreforms_fastapi/app/static/js/bootstrap.bundle.min.js
libreforms_fastapi/app/static/js/bootstrap.bundle.min.js.map
libreforms_fastapi/app/static/js/custom.js
libreforms_fastapi/app/static/js/datatables.js
libreforms_fastapi/app/static/js/jquery-3.7.1.min.js
libreforms_fastapi/app/static/js/jquery-3.7.1.min.map
libreforms_fastapi/app/static/js/plotly-2.29.1.min.js
libreforms_fastapi/app/static/js/monaco-editor-0.48.0/LICENSE
libreforms_fastapi/app/static/js/monaco-editor-0.48.0/ThirdPartyNotices.txt
libreforms_fastapi/app/static/js/monaco-editor-0.48.0/min/vs/loader.js
libreforms_fastapi/app/static/js/monaco-editor-0.48.0/min/vs/base/browser/ui/codicons/codicon/codicon.ttf
libreforms_fastapi/app/static/js/monaco-editor-0.48.0/min/vs/base/common/worker/simpleWorker.nls.de.js
libreforms_fastapi/app/static/js/monaco-editor-0.48.0/min/vs/base/common/worker/simpleWorker.nls.es.js
libreforms_fastapi/app/static/js/monaco-editor-0.48.0/min/vs/base/common/worker/simpleWorker.nls.fr.js
libreforms_fastapi/app/static/js/monaco-editor-0.48.0/min/vs/base/common/worker/simpleWorker.nls.it.js
libreforms_fastapi/app/static/js/monaco-editor-0.48.0/min/vs/base/common/worker/simpleWorker.nls.ja.js
libreforms_fastapi/app/static/js/monaco-editor-0.48.0/min/vs/base/common/worker/simpleWorker.nls.js
libreforms_fastapi/app/static/js/monaco-editor-0.48.0/min/vs/base/common/worker/simpleWorker.nls.ko.js
libreforms_fastapi/app/static/js/monaco-editor-0.48.0/min/vs/base/common/worker/simpleWorker.nls.ru.js
libreforms_fastapi/app/static/js/monaco-editor-0.48.0/min/vs/base/common/worker/simpleWorker.nls.zh-cn.js
libreforms_fastapi-1.0.9.dist-info/LICENSE
libreforms_fastapi-1.0.9.dist-info/METADATA
libreforms_fastapi-1.0.9.dist-info/WHEEL
libreforms_fastapi-1.0.9.dist-info/entry_points.txt
libreforms_fastapi-1.0.9.dist-info/top_level.txt
libreforms_fastapi-1.0.9.dist-info/RECORD
