Metadata-Version: 2.1
Name: libreforms_fastapi
Version: 1.0.9
Summary: FastAPI implementation of the libreForms spec
Home-page: https://github.com/signebedi/libreforms-fastapi
Author: Sig Janoska-Bedi
Author-email: signe@atreeus.com
Classifier: Programming Language :: Python :: 3.10
Classifier: License :: OSI Approved :: GNU Affero General Public License v3
Classifier: Operating System :: OS Independent
Requires-Python: >=3.10
License-File: LICENSE
Requires-Dist: cryptography <42.0.0
Requires-Dist: email-validator <3.0.0
Requires-Dist: fastapi <1.0.0
Requires-Dist: fuzzywuzzy <1.0.0
Requires-Dist: html-sanitizer <3.0.0
Requires-Dist: immutables <1.0.0
Requires-Dist: Jinja2 <4.0.0
Requires-Dist: Markdown <4.0.0
Requires-Dist: pydantic-settings <3.0.0
Requires-Dist: PyJWT <3.0.0
Requires-Dist: pymongo <5.0.0
Requires-Dist: python-Levenshtein <1.0.0
Requires-Dist: python-multipart <1.0.0
Requires-Dist: PyYAML <7.0.0
Requires-Dist: SQLAlchemy <3.0.0
Requires-Dist: sqlalchemy-signing <2.0.0
Requires-Dist: tinydb <5.0.0
Requires-Dist: uvicorn <1.0.0
Requires-Dist: watchdog <5.0.0
Provides-Extra: data
Requires-Dist: openpyxl <4.0.0 ; extra == 'data'
Requires-Dist: pandas <3.0.0 ; extra == 'data'
Requires-Dist: xlrd <3.0.0 ; extra == 'data'
Provides-Extra: mariadb
Requires-Dist: PyMySQL <2.0.0 ; extra == 'mariadb'
Provides-Extra: postgres
Requires-Dist: psycopg[binary] <4.0.0 ; extra == 'postgres'
Provides-Extra: saml
Requires-Dist: python3-saml <2.0.0 ; extra == 'saml'
